openapi_client/__init__.py
openapi_client/api_client.py
openapi_client/api_response.py
openapi_client/configuration.py
openapi_client/exceptions.py
openapi_client/py.typed
openapi_client/rest.py
openapi_client/api/__init__.py
openapi_client/api/chat_api.py
openapi_client/models/__init__.py
openapi_client/models/completion.py
openapi_client/models/completion_messages_inner.py
openapi_client/models/completion_result.py
openapi_client/models/completion_result_choices_inner.py
openapi_client/models/completion_result_choices_inner_message.py
openapi_client/models/completion_result_usage.py
suada_client/__init__.py
suada_client/api_client.py
suada_client/api_response.py
suada_client/configuration.py
suada_client/exceptions.py
suada_client/py.typed
suada_client/rest.py
suada_client/api/__init__.py
suada_client/api/chat_api.py
suada_client/models/__init__.py
suada_client/models/completion.py
suada_client/models/completion_messages_inner.py
suada_client/models/completion_result.py
suada_client/models/completion_result_choices_inner.py
suada_client/models/completion_result_choices_inner_message.py
suada_client/models/completion_result_usage.py
suada_client-1.0.0.dist-info/LICENSE
suada_client-1.0.0.dist-info/METADATA
suada_client-1.0.0.dist-info/WHEEL
suada_client-1.0.0.dist-info/top_level.txt
suada_client-1.0.0.dist-info/RECORD
